{
  "titleNameMap": {
    "educationList": "教育背景",
    "workExpList": "工作经历",
    "projectList": "项目经历",
    "skillList": "个人技能",
    "awardList": "更多信息",
    "workList": "个人作品",
    "aboutme": "自我介绍"
  },
  "avatar": {
    "src": "https://avatars.githubusercontent.com/u/15646325?v=4",
    "hidden": true
  },
  "profile": {
    "name": "唐锦仁(数据研发工程师)",
    "email": "tangjinren@foxmail.com",
    "mobile": "18182233556"
  },
  "educationList": [
    {
      "edu_time": [
        "2016.09.01",
        "2020.06.30"
      ],
      "school": "重庆工程学院",
      "major": "软件工程",
      "academic_degree": "本科"
    }
  ],
  "awardList": [
    {
      "award_info": "2016年-2017年学年第二学期君德杯大学生数学建模竞赛二等奖",
      "award_time": "2017"
    },
    {
      "award_info": "第六届“泰迪杯”数据挖掘挑战赛三等奖",
      "award_time": "2018"
    },
    {
      "award_info": "2017年-2018年国家单项奖学金",
      "award_time": "2018"
    },
    {
      "award_info": "2018年中国大学生计算机设计大赛重庆市级赛三等奖",
      "award_time": "2018"
    }
  ],
  "workExpList": [
    {
      "company_name": "四川锦程消费金融",
      "department_name": "信息技术部数据业务中心",
      "work_time": [
        "2019.11",
        null
      ],
      "work_desc": "1.参与数仓从0到1的搭建过程，工作内容从ODS层到DW层和DM层\n2.参与制定和研发了数仓统一调度SQL执行器，由python编写，使用format字符串的方式进行参数赋值，能够实现自定义参数扩展，为多种调度频率情境下的作业提供参数支持\n3.在TASKCTL平台基础上研发调度预警插件，对每日调度作业完成情况进行统计和通知\n4.研发报表层血缘分析程序，在应对底层依赖表变更时，给定表名、字段名和日期范围，能够快速精确定位影响范围并自动化刷数\n5.BI报表平台各部门日常报表研发工作\n6.taskctl管理员和运维人员\n7.数仓ODS层业务表入仓的维护"
    }
  ],
  "skillList": [
    {
      "skill_name": "pandas/numpy/pyhive/sqlalchemy",
      "skill_desc": "能够运用panda和numpy库配合ORM框架进行数据清洗，加工和数据透视",
      "skill_level": 80
    },
    {
      "skill_name": "SMARTBI",
      "skill_desc": "在工作中使用过SMART BI系统进行报表研发",
      "skill_level": 80
    },
    {
      "skill_name": "HIVE/SPARK/HDFS",
      "skill_desc": "简单了解hive on spark的运行模式，能够通过有向无环图、HDSF存储文件对hql进行常规的性能优化",
      "skill_level": 70
    },
    {
      "skill_name": "掌握",
      "skill_desc": "简单了解hive on spark的运行模式，能够通过有向无环图、HDSF存储文件对hql进行常规的性能优化",
      "skill_level": 70
    }
  ],
  "projectList": [
    {
      "project_name": "数据仓库研发",
      "project_role": "开发者/运维",
      "project_time": "2019.11 - 2020.11",
      "project_desc": "对Oracle数仓进行迁移和TDH数仓新增入仓业务表进行数据加载，清洗、加工和建模",
      "project_content": "1. 参与数仓从0到1的设计和开发 2. 参与数仓数据清洗规范的制定 3. 对数仓每日离线跑批任务进行分析和效率优化"
    },
    {
      "project_name": "SMART BI报表研发",
      "project_role": "开发者",
      "project_time": "2020.11 - 至今",
      "project_desc": "SMART BI为公司购买的企业级报表平台，可进行数据的图形化展示",
      "project_content": "接受公司各个部门的需求，使用SMART BI进行报表研发，为公司经营层和业务决策提供支持"
    },
    {
      "project_name": "个人数据采集网站",
      "project_role": "合作开发者",
      "project_time": "2021.7 - 至今",
      "project_desc": "对B站数据进行采集、清洗、存储和展示",
      "project_content": "使用python的request模块定时采集B站的图片和相关数据，使用Pandas模块进行数据清洗并用过ORM框架SQLAlchemy进行数据持久化，使用FastAPI编写网站数据展示的接口"
    }
  ],
  "workList": [],
  "aboutme": {
    "aboutme_desc": "有自我驱动力，能够在业余时间花费充足的精力进行数据相关开源技术的学习。在个人项目的开发过程中有阅读开源项目源码的习惯，通过IDE、调试模式等方式去学习和研究别人代码的优点，并应用于实践。\n会"
  },
  "theme": {
    "color": "#2f5785",
    "tagColor": "#8bc34a"
  }
}